[{"username":"bwlryq","mail":"bwlryq@flagmalo.fr","id":13,"password":"4269a2e7542d548e24fe768fcb5b23a0","isMod":true,"isAdmin":false,"note":"I must remember my password is cOIa22AISe3NOPyVGDmD. Semper Fidelis"},{"username":"Maxence","mail":"maxence@flagmalo.fr","id":21,"password":"e198b950734589de7a95f709e811d67c","isMod":true,"isAdmin":true,"note":"I'm a cool admin right ?"},{"username":"Yolande","mail":"Yolande@flagmalo.fr","id":0,"password":"8a5d4570ab5a6e814767f5a76df92eeb","isMod":false,"isAdmin":false,"note":"Fear is that little darkroom where negatives are developed."},{"username":"Kay","mail":"Kay@flagmalo.fr","id":1,"password":"85f93b7b3e65c76e6be0a5f1fda866cb","isMod":false,"isAdmin":false,"note":"Anyone who can handle a needle convincingly can make us see a thread which is not there."},{"username":"Emily","mail":"Emily@flagmalo.fr","id":2,"password":"22a70089b361af97cad8d2b2e2205765","isMod":false,"isAdmin":false,"note":""},{"username":"Beatrice","mail":"Beatrice@flagmalo.fr","id":3,"password":"b25f4957055ac319dd708dd49de2f837","isMod":false,"isAdmin":false,"note":"He who hesitates is not only lost, but miles from the next exit."},{"username":"CarTyra","mail":"CarTyra@flagmalo.fr","id":4,"password":"bb1243fa3f774707f4b29de596aa4405","isMod":false,"isAdmin":false,"note":"War is much too serious a matter to be entrusted to the military."},{"username":"ShieldGold","mail":"ShieldGold@flagmalo.fr","id":5,"password":"93dd23505ae83cbd250ccddde61c9271","isMod":false,"isAdmin":false,"note":"Eat a live toad the first thing in the morning and nothing worse will happen to you the rest of the day."},{"username":"BannanaFlying","mail":"BannanaFlying@flagmalo.fr","id":6,"password":"16959529a093bdf34b043a2ee8ec4ba9","isMod":false,"isAdmin":false,"note":"Good manners are just a way of showing other people that we have respect for them."},{"username":"DocteurPredator","mail":"DocteurPredator@flagmalo.fr","id":7,"password":"80f803b62e6e895636ed2f725dc0ad79","isMod":false,"isAdmin":false,"note":"You get fifteen democrats in a room, and you get twenty opinions."},{"username":"WarriorBeta","mail":"WarriorBeta@flagmalo.fr","id":8,"password":"4e40d8a8209edbc1e0f1cb8515ced3bd","isMod":false,"isAdmin":false,"note":""},{"username":"EagleColossus","mail":"EagleColossus@flagmalo.fr","id":9,"password":"9fdf8339d42401ee196cff85a1d619a1","isMod":false,"isAdmin":false,"note":"You have a choice in this world, I believe, about how to tell sad stories."},{"username":"RikuBeta","mail":"RikuBeta@flagmalo.fr","id":10,"password":"bbf7c1ec058b3004cd0a3d17d62fb533","isMod":false,"isAdmin":false,"note":"A bore is a man who, when you ask him how he is, tells you."},{"username":"BoisSteel","mail":"BoisSteel@flagmalo.fr","id":11,"password":"be9f4e25c06604e54e005151c8b71a13","isMod":false,"isAdmin":false,"note":"Enjoy your own life without comparing it with that of another."},{"username":"SaleMamba","mail":"SaleMamba@flagmalo.fr","id":12,"password":"d07a81922da6055738996cfe46a5eedc","isMod":false,"isAdmin":false,"note":"The greatest challenge to any thinker is stating the problem in a way that will allow a solution."},{"username":"BearMaj","mail":"BearMaj@flagmalo.fr","id":14,"password":"ad3e90636e7c768bba239da143d5b491","isMod":false,"isAdmin":false,"note":"The secret to success in life is known only to those who have not succeeded."},{"username":"GodzillaSale","mail":"GodzillaSale@flagmalo.fr","id":15,"password":"e4b814a67f5889f47d2c4e79ab1e1c82","isMod":false,"isAdmin":false,"note":"Get away from the crowd when you can. Keep yourself to yourself, if only for a few hours daily."},{"username":"NoobSteel","mail":"NoobSteel@flagmalo.fr","id":16,"password":"f293b2fb323b7aea326f8e6360640a0f","isMod":false,"isAdmin":false,"note":"The lion and the calf shall lie down together but the calf won't get much sleep."},{"username":"NightTyra","mail":"NightTyra@flagmalo.fr","id":17,"password":"ebb394271f0c22be0a8257d0580375e5","isMod":false,"isAdmin":false,"note":"I feel about airplanes the way I feel about diets. It seems to me they are wonderful things for other people to go on."},{"username":"B\u0153ufFreedom","mail":"B\u0153ufFreedom@flagmalo.fr","id":18,"password":"47d3264f561327620a0d31cb22338ec0","isMod":false,"isAdmin":false,"note":"The gambling known as business looks with austere disfavor upon the business known as gambling."},{"username":"LegendSushi","mail":"LegendSushi@flagmalo.fr","id":19,"password":"75599860489bc9bde0d97328f977d61b","isMod":false,"isAdmin":false,"note":"Criticism is prejudice made plausible."},{"username":"WhiteCar","mail":"WhiteCar@flagmalo.fr","id":20,"password":"7074cf08559dff95e5b577fe0cc4325a","isMod":false,"isAdmin":false,"note":"Honest criticism is hard to take, particularly from a relative, a friend, an acquaintance, or a stranger."}]